autocare/__init__.py
autocare/client.py
autocare-0.1.0.dist-info/licenses/LICENSE
autocare-0.1.0.dist-info/METADATA
autocare-0.1.0.dist-info/WHEEL
autocare-0.1.0.dist-info/top_level.txt
autocare-0.1.0.dist-info/RECORD
