Metadata-Version: 2.4
Name: autocare
Version: 0.1.0
Summary: Python client for the AutoCare API
Author-email: Andy Craze <acraze@nexamotiongroup.com>
License: MIT
Requires-Python: >=3.13
License-File: LICENSE
Requires-Dist: requests>=2.32.4
Dynamic: license-file
